countries/__init__.py
countries/admin.py
countries/data_io.py
countries/models.py
countries/migrations/0001_initial.py
countries/migrations/0002_auto_20150527_1912.py
countries/migrations/0003_auto_20150527_1928.py
countries/migrations/0004_auto_20150528_1248.py
countries/migrations/0005_auto_20160607_1416.py
countries/migrations/0006_auto_20160607_1742.py
countries/migrations/0007_auto_20160607_1908.py
countries/migrations/__init__.py
countries/settings/__init__.py
countries/settings/test_settings.py
countries/tests/__init__.py
countries/tests/models_tests.py
countries/tests/runtests.py
valuehorizon_countries-0.2.1.dist-info/DESCRIPTION.rst
valuehorizon_countries-0.2.1.dist-info/METADATA
valuehorizon_countries-0.2.1.dist-info/RECORD
valuehorizon_countries-0.2.1.dist-info/WHEEL
valuehorizon_countries-0.2.1.dist-info/metadata.json
valuehorizon_countries-0.2.1.dist-info/top_level.txt
