Metadata-Version: 2.0
Name: valuehorizon-countries
Version: 0.2.1
Summary: A Django-based Countries data toolkit. Part of the Valuehorizon application ecosystem.
Requires-Dist: valuehorizon-forex
Provides-Extra: dev
Requires-Dist: flake8; extra == 'dev'
